{
  "2026-04-10": [
    {
      "timestamp": "2026-04-10T02:05:10.983366",
      "health": {
        "engagement_agent": {
          "last_run": "2026-04-09T22:00:17.711960",
          "runs_today": 6,
          "recent_errors": 0,
          "comments_processed": 0,
          "status": "stale"
        },
        "engagement_bot": {
          "last_run": "2026-04-09T19:30:13.673155",
          "runs_today": 1,
          "recent_errors": 0,
          "status": "stale"
        }
      },
      "metrics": {
        "platform_stats": {
          "instagram": {
            "posts": 10,
            "total_likes": 12,
            "total_comments": 3,
            "total_saves": 5,
            "total_reposts": 0,
            "api_available": true,
            "avg_engagement": 1.5,
            "engagement_rate": 0.15
          },
          "bluesky": {
            "posts": 10,
            "total_likes": 1,
            "total_comments": 0,
            "total_saves": 0,
            "total_reposts": 0,
            "api_available": true,
            "avg_engagement": 0.1,
            "engagement_rate": 0.01
          },
          "x": {
            "posts": 7,
            "total_likes": 0,
            "total_comments": 0,
            "total_saves": 0,
            "total_reposts": 0,
            "api_available": true,
            "avg_engagement": 0.0,
            "engagement_rate": 0.0
          },
          "tiktok": {
            "posts": 9,
            "total_likes": 0,
            "total_comments": 0,
            "total_saves": 0,
            "total_reposts": 0,
            "api_available": true,
            "avg_engagement": 0.0,
            "engagement_rate": 0.0
          },
          "threads": {
            "posts": 9,
            "total_likes": 0,
            "total_comments": 0,
            "total_saves": 0,
            "total_reposts": 0,
            "api_available": true,
            "avg_engagement": 0.0,
            "engagement_rate": 0.0
          }
        },
        "comment_stats": {
          "total_comments_seen": 0,
          "replies_sent": 0,
          "response_rate": 0.0,
          "recent_activity": false
        },
        "overall_engagement_rate": 0.35555555555555557,
        "total_posts": 45
      },
      "alerts": [
        {
          "type": "agent_stale",
          "severity": "high",
          "message": "engagement_agent hasn't run in 4+ hours",
          "agent": "engagement_agent"
        },
        {
          "type": "agent_stale",
          "severity": "high",
          "message": "engagement_bot hasn't run in 4+ hours",
          "agent": "engagement_bot"
        },
        {
          "type": "no_comments",
          "severity": "low",
          "message": "No comments processed in the last 24 hours",
          "suggestion": "Check if comment API endpoints are working"
        }
      ],
      "summary": {
        "agents_healthy": 0,
        "total_alerts": 3,
        "high_priority_alerts": 2
      }
    },
    {
      "timestamp": "2026-04-10T08:01:44.395286",
      "health": {
        "engagement_agent": {
          "last_run": "2026-04-09T22:00:17.711960",
          "runs_today": 9,
          "recent_errors": 0,
          "comments_processed": 0,
          "status": "stale"
        },
        "engagement_bot": {
          "last_run": "2026-04-09T19:30:13.673155",
          "runs_today": 2,
          "recent_errors": 0,
          "status": "stale"
        }
      },
      "metrics": {
        "platform_stats": {
          "instagram": {
            "posts": 13,
            "total_likes": 12,
            "total_comments": 3,
            "total_saves": 5,
            "total_reposts": 0,
            "api_available": true,
            "avg_engagement": 1.1538461538461537,
            "engagement_rate": 0.08875739644970414
          },
          "bluesky": {
            "posts": 13,
            "total_likes": 1,
            "total_comments": 0,
            "total_saves": 0,
            "total_reposts": 0,
            "api_available": true,
            "avg_engagement": 0.07692307692307693,
            "engagement_rate": 0.00591715976331361
          },
          "x": {
            "posts": 10,
            "total_likes": 0,
            "total_comments": 0,
            "total_saves": 0,
            "total_reposts": 0,
            "api_available": true,
            "avg_engagement": 0.0,
            "engagement_rate": 0.0
          },
          "tiktok": {
            "posts": 12,
            "total_likes": 0,
            "total_comments": 0,
            "total_saves": 0,
            "total_reposts": 0,
            "api_available": true,
            "avg_engagement": 0.0,
            "engagement_rate": 0.0
          },
          "threads": {
            "posts": 11,
            "total_likes": 0,
            "total_comments": 0,
            "total_saves": 0,
            "total_reposts": 0,
            "api_available": true,
            "avg_engagement": 0.0,
            "engagement_rate": 0.0
          }
        },
        "comment_stats": {
          "total_comments_seen": 0,
          "replies_sent": 0,
          "response_rate": 0.0,
          "recent_activity": false
        },
        "overall_engagement_rate": 0.2711864406779661,
        "total_posts": 59
      },
      "alerts": [
        {
          "type": "agent_stale",
          "severity": "high",
          "message": "engagement_agent hasn't run in 4+ hours",
          "agent": "engagement_agent"
        },
        {
          "type": "agent_stale",
          "severity": "high",
          "message": "engagement_bot hasn't run in 4+ hours",
          "agent": "engagement_bot"
        },
        {
          "type": "no_comments",
          "severity": "low",
          "message": "No comments processed in the last 24 hours",
          "suggestion": "Check if comment API endpoints are working"
        }
      ],
      "summary": {
        "agents_healthy": 0,
        "total_alerts": 3,
        "high_priority_alerts": 2
      }
    },
    {
      "timestamp": "2026-04-10T08:03:31.753744",
      "health": {
        "engagement_agent": {
          "last_run": "2026-04-09T22:00:17.711960",
          "runs_today": 10,
          "recent_errors": 0,
          "comments_processed": 0,
          "status": "stale"
        },
        "engagement_bot": {
          "last_run": "2026-04-09T19:30:13.673155",
          "runs_today": 3,
          "recent_errors": 0,
          "status": "stale"
        }
      },
      "metrics": {
        "platform_stats": {
          "instagram": {
            "posts": 13,
            "total_likes": 12,
            "total_comments": 3,
            "total_saves": 5,
            "total_reposts": 0,
            "api_available": true,
            "avg_engagement": 1.1538461538461537,
            "engagement_rate": 0.08875739644970414
          },
          "bluesky": {
            "posts": 13,
            "total_likes": 1,
            "total_comments": 0,
            "total_saves": 0,
            "total_reposts": 0,
            "api_available": true,
            "avg_engagement": 0.07692307692307693,
            "engagement_rate": 0.00591715976331361
          },
          "x": {
            "posts": 10,
            "total_likes": 0,
            "total_comments": 0,
            "total_saves": 0,
            "total_reposts": 0,
            "api_available": true,
            "avg_engagement": 0.0,
            "engagement_rate": 0.0
          },
          "tiktok": {
            "posts": 12,
            "total_likes": 0,
            "total_comments": 0,
            "total_saves": 0,
            "total_reposts": 0,
            "api_available": true,
            "avg_engagement": 0.0,
            "engagement_rate": 0.0
          },
          "threads": {
            "posts": 11,
            "total_likes": 0,
            "total_comments": 0,
            "total_saves": 0,
            "total_reposts": 0,
            "api_available": true,
            "avg_engagement": 0.0,
            "engagement_rate": 0.0
          }
        },
        "comment_stats": {
          "total_comments_seen": 0,
          "replies_sent": 0,
          "response_rate": 0.0,
          "recent_activity": false
        },
        "overall_engagement_rate": 0.2711864406779661,
        "total_posts": 59
      },
      "alerts": [
        {
          "type": "agent_stale",
          "severity": "high",
          "message": "engagement_agent hasn't run in 4+ hours",
          "agent": "engagement_agent"
        },
        {
          "type": "agent_stale",
          "severity": "high",
          "message": "engagement_bot hasn't run in 4+ hours",
          "agent": "engagement_bot"
        },
        {
          "type": "no_comments",
          "severity": "low",
          "message": "No comments processed in the last 24 hours",
          "suggestion": "Check if comment API endpoints are working"
        }
      ],
      "summary": {
        "agents_healthy": 0,
        "total_alerts": 3,
        "high_priority_alerts": 2
      }
    },
    {
      "timestamp": "2026-04-10T10:01:45.662948",
      "health": {
        "engagement_agent": {
          "last_run": "2026-04-09T22:00:17.711960",
          "runs_today": 11,
          "recent_errors": 0,
          "comments_processed": 0,
          "status": "stale"
        },
        "engagement_bot": {
          "last_run": "2026-04-09T19:30:13.673155",
          "runs_today": 4,
          "recent_errors": 0,
          "status": "stale"
        }
      },
      "metrics": {
        "platform_stats": {
          "instagram": {
            "posts": 13,
            "total_likes": 12,
            "total_comments": 3,
            "total_saves": 5,
            "total_reposts": 0,
            "api_available": true,
            "avg_engagement": 1.1538461538461537,
            "engagement_rate": 0.08875739644970414
          },
          "bluesky": {
            "posts": 13,
            "total_likes": 1,
            "total_comments": 0,
            "total_saves": 0,
            "total_reposts": 0,
            "api_available": true,
            "avg_engagement": 0.07692307692307693,
            "engagement_rate": 0.00591715976331361
          },
          "x": {
            "posts": 10,
            "total_likes": 0,
            "total_comments": 0,
            "total_saves": 0,
            "total_reposts": 0,
            "api_available": true,
            "avg_engagement": 0.0,
            "engagement_rate": 0.0
          },
          "tiktok": {
            "posts": 12,
            "total_likes": 0,
            "total_comments": 0,
            "total_saves": 0,
            "total_reposts": 0,
            "api_available": true,
            "avg_engagement": 0.0,
            "engagement_rate": 0.0
          },
          "threads": {
            "posts": 11,
            "total_likes": 0,
            "total_comments": 0,
            "total_saves": 0,
            "total_reposts": 0,
            "api_available": true,
            "avg_engagement": 0.0,
            "engagement_rate": 0.0
          }
        },
        "comment_stats": {
          "total_comments_seen": 0,
          "replies_sent": 0,
          "response_rate": 0.0,
          "recent_activity": false
        },
        "overall_engagement_rate": 0.2711864406779661,
        "total_posts": 59
      },
      "alerts": [
        {
          "type": "agent_stale",
          "severity": "high",
          "message": "engagement_agent hasn't run in 4+ hours",
          "agent": "engagement_agent"
        },
        {
          "type": "agent_stale",
          "severity": "high",
          "message": "engagement_bot hasn't run in 4+ hours",
          "agent": "engagement_bot"
        },
        {
          "type": "no_comments",
          "severity": "low",
          "message": "No comments processed in the last 24 hours",
          "suggestion": "Check if comment API endpoints are working"
        }
      ],
      "summary": {
        "agents_healthy": 0,
        "total_alerts": 3,
        "high_priority_alerts": 2
      }
    },
    {
      "timestamp": "2026-04-10T10:01:50.722131",
      "health": {
        "engagement_agent": {
          "last_run": "2026-04-09T22:00:17.711960",
          "runs_today": 11,
          "recent_errors": 0,
          "comments_processed": 0,
          "status": "stale"
        },
        "engagement_bot": {
          "last_run": "2026-04-09T19:30:13.673155",
          "runs_today": 4,
          "recent_errors": 0,
          "status": "stale"
        }
      },
      "metrics": {
        "platform_stats": {
          "instagram": {
            "posts": 13,
            "total_likes": 12,
            "total_comments": 3,
            "total_saves": 5,
            "total_reposts": 0,
            "api_available": true,
            "avg_engagement": 1.1538461538461537,
            "engagement_rate": 0.08875739644970414
          },
          "bluesky": {
            "posts": 13,
            "total_likes": 1,
            "total_comments": 0,
            "total_saves": 0,
            "total_reposts": 0,
            "api_available": true,
            "avg_engagement": 0.07692307692307693,
            "engagement_rate": 0.00591715976331361
          },
          "x": {
            "posts": 10,
            "total_likes": 0,
            "total_comments": 0,
            "total_saves": 0,
            "total_reposts": 0,
            "api_available": true,
            "avg_engagement": 0.0,
            "engagement_rate": 0.0
          },
          "tiktok": {
            "posts": 12,
            "total_likes": 0,
            "total_comments": 0,
            "total_saves": 0,
            "total_reposts": 0,
            "api_available": true,
            "avg_engagement": 0.0,
            "engagement_rate": 0.0
          },
          "threads": {
            "posts": 11,
            "total_likes": 0,
            "total_comments": 0,
            "total_saves": 0,
            "total_reposts": 0,
            "api_available": true,
            "avg_engagement": 0.0,
            "engagement_rate": 0.0
          }
        },
        "comment_stats": {
          "total_comments_seen": 0,
          "replies_sent": 0,
          "response_rate": 0.0,
          "recent_activity": false
        },
        "overall_engagement_rate": 0.2711864406779661,
        "total_posts": 59
      },
      "alerts": [
        {
          "type": "agent_stale",
          "severity": "high",
          "message": "engagement_agent hasn't run in 4+ hours",
          "agent": "engagement_agent"
        },
        {
          "type": "agent_stale",
          "severity": "high",
          "message": "engagement_bot hasn't run in 4+ hours",
          "agent": "engagement_bot"
        },
        {
          "type": "no_comments",
          "severity": "low",
          "message": "No comments processed in the last 24 hours",
          "suggestion": "Check if comment API endpoints are working"
        }
      ],
      "summary": {
        "agents_healthy": 0,
        "total_alerts": 3,
        "high_priority_alerts": 2
      }
    },
    {
      "timestamp": "2026-04-10T12:01:33.904040",
      "health": {
        "engagement_agent": {
          "last_run": "2026-04-09T22:00:17.711960",
          "runs_today": 14,
          "recent_errors": 0,
          "comments_processed": 0,
          "status": "stale"
        },
        "engagement_bot": {
          "last_run": "2026-04-09T19:30:13.673155",
          "runs_today": 6,
          "recent_errors": 0,
          "status": "stale"
        }
      },
      "metrics": {
        "platform_stats": {
          "instagram": {
            "posts": 13,
            "total_likes": 12,
            "total_comments": 3,
            "total_saves": 5,
            "total_reposts": 0,
            "api_available": true,
            "avg_engagement": 1.1538461538461537,
            "engagement_rate": 0.08875739644970414
          },
          "bluesky": {
            "posts": 13,
            "total_likes": 1,
            "total_comments": 0,
            "total_saves": 0,
            "total_reposts": 0,
            "api_available": true,
            "avg_engagement": 0.07692307692307693,
            "engagement_rate": 0.00591715976331361
          },
          "x": {
            "posts": 10,
            "total_likes": 0,
            "total_comments": 0,
            "total_saves": 0,
            "total_reposts": 0,
            "api_available": true,
            "avg_engagement": 0.0,
            "engagement_rate": 0.0
          },
          "tiktok": {
            "posts": 12,
            "total_likes": 0,
            "total_comments": 0,
            "total_saves": 0,
            "total_reposts": 0,
            "api_available": true,
            "avg_engagement": 0.0,
            "engagement_rate": 0.0
          },
          "threads": {
            "posts": 11,
            "total_likes": 0,
            "total_comments": 0,
            "total_saves": 0,
            "total_reposts": 0,
            "api_available": true,
            "avg_engagement": 0.0,
            "engagement_rate": 0.0
          }
        },
        "comment_stats": {
          "total_comments_seen": 0,
          "replies_sent": 0,
          "response_rate": 0.0,
          "recent_activity": false
        },
        "overall_engagement_rate": 0.2711864406779661,
        "total_posts": 59
      },
      "alerts": [
        {
          "type": "agent_stale",
          "severity": "high",
          "message": "engagement_agent hasn't run in 4+ hours",
          "agent": "engagement_agent"
        },
        {
          "type": "agent_stale",
          "severity": "high",
          "message": "engagement_bot hasn't run in 4+ hours",
          "agent": "engagement_bot"
        },
        {
          "type": "no_comments",
          "severity": "low",
          "message": "No comments processed in the last 24 hours",
          "suggestion": "Check if comment API endpoints are working"
        }
      ],
      "summary": {
        "agents_healthy": 0,
        "total_alerts": 3,
        "high_priority_alerts": 2
      }
    },
    {
      "timestamp": "2026-04-10T12:11:07.457730",
      "health": {
        "engagement_agent": {
          "last_run": "2026-04-09T22:00:17.711960",
          "runs_today": 20,
          "recent_errors": 0,
          "comments_processed": 0,
          "status": "stale"
        },
        "engagement_bot": {
          "last_run": "2026-04-09T19:30:13.673155",
          "runs_today": 11,
          "recent_errors": 0,
          "status": "stale"
        }
      },
      "metrics": {
        "platform_stats": {
          "instagram": {
            "posts": 13,
            "total_likes": 12,
            "total_comments": 3,
            "total_saves": 5,
            "total_reposts": 0,
            "api_available": true,
            "avg_engagement": 1.1538461538461537,
            "engagement_rate": 0.08875739644970414
          },
          "bluesky": {
            "posts": 13,
            "total_likes": 1,
            "total_comments": 0,
            "total_saves": 0,
            "total_reposts": 0,
            "api_available": true,
            "avg_engagement": 0.07692307692307693,
            "engagement_rate": 0.00591715976331361
          },
          "x": {
            "posts": 10,
            "total_likes": 0,
            "total_comments": 0,
            "total_saves": 0,
            "total_reposts": 0,
            "api_available": true,
            "avg_engagement": 0.0,
            "engagement_rate": 0.0
          },
          "tiktok": {
            "posts": 12,
            "total_likes": 0,
            "total_comments": 0,
            "total_saves": 0,
            "total_reposts": 0,
            "api_available": true,
            "avg_engagement": 0.0,
            "engagement_rate": 0.0
          },
          "threads": {
            "posts": 11,
            "total_likes": 0,
            "total_comments": 0,
            "total_saves": 0,
            "total_reposts": 0,
            "api_available": true,
            "avg_engagement": 0.0,
            "engagement_rate": 0.0
          }
        },
        "comment_stats": {
          "total_comments_seen": 0,
          "replies_sent": 0,
          "response_rate": 0.0,
          "recent_activity": false
        },
        "overall_engagement_rate": 0.2711864406779661,
        "total_posts": 59
      },
      "alerts": [
        {
          "type": "agent_stale",
          "severity": "high",
          "message": "engagement_agent hasn't run in 4+ hours",
          "agent": "engagement_agent"
        },
        {
          "type": "agent_stale",
          "severity": "high",
          "message": "engagement_bot hasn't run in 4+ hours",
          "agent": "engagement_bot"
        },
        {
          "type": "no_comments",
          "severity": "low",
          "message": "No comments processed in the last 24 hours",
          "suggestion": "Check if comment API endpoints are working"
        }
      ],
      "summary": {
        "agents_healthy": 0,
        "total_alerts": 3,
        "high_priority_alerts": 2
      }
    },
    {
      "timestamp": "2026-04-10T16:01:54.533887",
      "health": {
        "engagement_agent": {
          "last_run": "2026-04-09T22:00:17.711960",
          "runs_today": 22,
          "recent_errors": 0,
          "comments_processed": 0,
          "status": "stale"
        },
        "engagement_bot": {
          "last_run": "2026-04-09T19:30:13.673155",
          "runs_today": 13,
          "recent_errors": 0,
          "status": "stale"
        }
      },
      "metrics": {
        "platform_stats": {
          "instagram": {
            "posts": 13,
            "total_likes": 12,
            "total_comments": 3,
            "total_saves": 5,
            "total_reposts": 0,
            "api_available": true,
            "avg_engagement": 1.1538461538461537,
            "engagement_rate": 0.08875739644970414
          },
          "bluesky": {
            "posts": 13,
            "total_likes": 1,
            "total_comments": 0,
            "total_saves": 0,
            "total_reposts": 0,
            "api_available": true,
            "avg_engagement": 0.07692307692307693,
            "engagement_rate": 0.00591715976331361
          },
          "x": {
            "posts": 10,
            "total_likes": 0,
            "total_comments": 0,
            "total_saves": 0,
            "total_reposts": 0,
            "api_available": true,
            "avg_engagement": 0.0,
            "engagement_rate": 0.0
          },
          "tiktok": {
            "posts": 12,
            "total_likes": 0,
            "total_comments": 0,
            "total_saves": 0,
            "total_reposts": 0,
            "api_available": true,
            "avg_engagement": 0.0,
            "engagement_rate": 0.0
          },
          "threads": {
            "posts": 11,
            "total_likes": 0,
            "total_comments": 0,
            "total_saves": 0,
            "total_reposts": 0,
            "api_available": true,
            "avg_engagement": 0.0,
            "engagement_rate": 0.0
          }
        },
        "comment_stats": {
          "total_comments_seen": 0,
          "replies_sent": 0,
          "response_rate": 0.0,
          "recent_activity": false
        },
        "overall_engagement_rate": 0.2711864406779661,
        "total_posts": 59
      },
      "alerts": [
        {
          "type": "agent_stale",
          "severity": "high",
          "message": "engagement_agent hasn't run in 4+ hours",
          "agent": "engagement_agent"
        },
        {
          "type": "agent_stale",
          "severity": "high",
          "message": "engagement_bot hasn't run in 4+ hours",
          "agent": "engagement_bot"
        },
        {
          "type": "no_comments",
          "severity": "low",
          "message": "No comments processed in the last 24 hours",
          "suggestion": "Check if comment API endpoints are working"
        }
      ],
      "summary": {
        "agents_healthy": 0,
        "total_alerts": 3,
        "high_priority_alerts": 2
      }
    }
  ],
  "2026-04-11": [
    {
      "timestamp": "2026-04-11T22:01:35.593863",
      "health": {
        "engagement_agent": {
          "last_run": "2026-04-10T20:04:02.170312",
          "runs_today": 0,
          "recent_errors": 0,
          "comments_processed": 0,
          "status": "stale"
        },
        "engagement_bot": {
          "last_run": "2026-04-10T16:02:17.360402",
          "runs_today": 1,
          "recent_errors": 0,
          "status": "stale"
        }
      },
      "metrics": {
        "platform_stats": {
          "instagram": {
            "posts": 16,
            "total_likes": 12,
            "total_comments": 3,
            "total_saves": 5,
            "total_reposts": 0,
            "api_available": true,
            "avg_engagement": 0.9375,
            "engagement_rate": 0.05859375
          },
          "bluesky": {
            "posts": 17,
            "total_likes": 2,
            "total_comments": 0,
            "total_saves": 0,
            "total_reposts": 0,
            "api_available": true,
            "avg_engagement": 0.11764705882352941,
            "engagement_rate": 0.006920415224913495
          },
          "x": {
            "posts": 14,
            "total_likes": 0,
            "total_comments": 0,
            "total_saves": 0,
            "total_reposts": 0,
            "api_available": true,
            "avg_engagement": 0.0,
            "engagement_rate": 0.0
          },
          "tiktok": {
            "posts": 15,
            "total_likes": 0,
            "total_comments": 0,
            "total_saves": 0,
            "total_reposts": 0,
            "api_available": true,
            "avg_engagement": 0.0,
            "engagement_rate": 0.0
          },
          "threads": {
            "posts": 14,
            "total_likes": 0,
            "total_comments": 0,
            "total_saves": 0,
            "total_reposts": 0,
            "api_available": true,
            "avg_engagement": 0.0,
            "engagement_rate": 0.0
          }
        },
        "comment_stats": {
          "total_comments_seen": 0,
          "replies_sent": 10,
          "response_rate": 0.0,
          "recent_activity": true
        },
        "overall_engagement_rate": 0.2236842105263158,
        "total_posts": 76
      },
      "alerts": [
        {
          "type": "agent_stale",
          "severity": "high",
          "message": "engagement_agent hasn't run in 4+ hours",
          "agent": "engagement_agent"
        },
        {
          "type": "agent_stale",
          "severity": "high",
          "message": "engagement_bot hasn't run in 4+ hours",
          "agent": "engagement_bot"
        }
      ],
      "summary": {
        "agents_healthy": 0,
        "total_alerts": 2,
        "high_priority_alerts": 2
      }
    },
    {
      "timestamp": "2026-04-11T22:07:25.984597",
      "health": {
        "engagement_agent": {
          "last_run": "2026-04-10T20:04:02.170312",
          "runs_today": 0,
          "recent_errors": 0,
          "comments_processed": 0,
          "status": "stale"
        },
        "engagement_bot": {
          "last_run": "2026-04-10T16:02:17.360402",
          "runs_today": 1,
          "recent_errors": 0,
          "status": "stale"
        }
      },
      "metrics": {
        "platform_stats": {
          "instagram": {
            "posts": 16,
            "total_likes": 12,
            "total_comments": 3,
            "total_saves": 5,
            "total_reposts": 0,
            "api_available": true,
            "avg_engagement": 0.9375,
            "engagement_rate": 0.05859375
          },
          "bluesky": {
            "posts": 17,
            "total_likes": 2,
            "total_comments": 0,
            "total_saves": 0,
            "total_reposts": 0,
            "api_available": true,
            "avg_engagement": 0.11764705882352941,
            "engagement_rate": 0.006920415224913495
          },
          "x": {
            "posts": 14,
            "total_likes": 0,
            "total_comments": 0,
            "total_saves": 0,
            "total_reposts": 0,
            "api_available": true,
            "avg_engagement": 0.0,
            "engagement_rate": 0.0
          },
          "tiktok": {
            "posts": 15,
            "total_likes": 0,
            "total_comments": 0,
            "total_saves": 0,
            "total_reposts": 0,
            "api_available": true,
            "avg_engagement": 0.0,
            "engagement_rate": 0.0
          },
          "threads": {
            "posts": 14,
            "total_likes": 0,
            "total_comments": 0,
            "total_saves": 0,
            "total_reposts": 0,
            "api_available": true,
            "avg_engagement": 0.0,
            "engagement_rate": 0.0
          }
        },
        "comment_stats": {
          "total_comments_seen": 0,
          "replies_sent": 10,
          "response_rate": 0.0,
          "recent_activity": true
        },
        "overall_engagement_rate": 0.2236842105263158,
        "total_posts": 76
      },
      "alerts": [
        {
          "type": "agent_stale",
          "severity": "high",
          "message": "engagement_agent hasn't run in 4+ hours",
          "agent": "engagement_agent"
        },
        {
          "type": "agent_stale",
          "severity": "high",
          "message": "engagement_bot hasn't run in 4+ hours",
          "agent": "engagement_bot"
        }
      ],
      "summary": {
        "agents_healthy": 0,
        "total_alerts": 2,
        "high_priority_alerts": 2
      }
    }
  ]
}